NHDPlus_Extractor/NHDPlus_Extractor.py
NHDPlus_Extractor/__init__.py
NHDPlus_Extractor/flowline.py
NHDPlus_Extractor/vectorutils.py
PyNHDPlus/NHDPlus_Extractor.py
PyNHDPlus/__init__.py
PyNHDPlus/flowline.py
PyNHDPlus/vectorutils.py
PyNHDPlus-1.8.5.dist-info/DESCRIPTION.rst
PyNHDPlus-1.8.5.dist-info/METADATA
PyNHDPlus-1.8.5.dist-info/RECORD
PyNHDPlus-1.8.5.dist-info/WHEEL
PyNHDPlus-1.8.5.dist-info/metadata.json
PyNHDPlus-1.8.5.dist-info/top_level.txt
