Metadata-Version: 2.0
Name: PyNHDPlus
Version: 1.8.5
Summary: Tools to download and manipulate the NHDPlus V2 dataset
Home-page: https://github.com/Msawtelle/PyNHDPLUS
Author: Mitchell Sawtelle
Author-email: mitchell.sawtelle@okstate.edu
License: GNU
Keywords: NHDPlus,GIS,Hydrography
Platform: UNKNOWN
Requires-Dist: numpy
Requires-Dist: gdal
Requires-Dist: matplotlib
